golftracker/__init__.py
golftracker/canny_edge_detector.py
golftracker/canny_edge_params.py
golftracker/club_head_detector.py
golftracker/club_head_params.py
golftracker/club_head_result.py
golftracker/double_pendlum.py
golftracker/file_utils.py
golftracker/geom.py
golftracker/golf_swing.py
golftracker/golf_swing_factory.py
golftracker/golf_swing_repository.py
golftracker/gt_const.py
golftracker/hough_line_detector.py
golftracker/hough_line_params.py
golftracker/image_operations.py
golftracker/image_utils.py
golftracker/media_pipe_landmarks.py
golftracker/media_pipe_operation.py
golftracker/path_model.py
golftracker/pose_model.py
golftracker/pose_result.py
golftracker/video_utils.py
golftracker-2.0.dist-info/LICENSE.txt
golftracker-2.0.dist-info/METADATA
golftracker-2.0.dist-info/WHEEL
golftracker-2.0.dist-info/entry_points.txt
golftracker-2.0.dist-info/top_level.txt
golftracker-2.0.dist-info/RECORD
