Metadata-Version: 2.1
Name: golftracker
Version: 2.0
Summary: Use open cv to detect critical elements in a golf swing.
Home-page: https://github.com/sanjeevs/golftracker
Author: Sanjeev Singh
Author-email: snjvsingh123@gmail.com
License: UNKNOWN
Platform: UNKNOWN
Classifier: Programming Language :: Python :: 3
Classifier: Programming Language :: Python :: 3.6
Classifier: Programming Language :: Python :: 3.7
Classifier: License :: OSI Approved :: MIT License
Classifier: Operating System :: OS Independent
Classifier: Development Status :: 3 - Alpha
License-File: LICENSE.txt
Requires-Dist: opencv-contrib-python
Requires-Dist: protobuf ==3.20.0
Requires-Dist: mediapipe ==0.8.10
Requires-Dist: numpy
Requires-Dist: scikit-learn
Requires-Dist: pandas
Provides-Extra: dev
Requires-Dist: pytest >=3.7 ; extra == 'dev'
Requires-Dist: check-manifest ; extra == 'dev'
Requires-Dist: twine ; extra == 'dev'
